[
  {
    "id": "894854262",
    "title": "QuintoAndar ",
    "neighborhood": "",
    "url": "https://www.quintoandar.com.br/imovel/894854262/alugar/apartamento-2-quartos-itaim-bibi-sao-paulo",
    "rent": 0,
    "condo": 0,
    "iptu": 0,
    "area": 0,
    "bedrooms": 0,
    "bathrooms": 0,
    "parking": 0,
    "transit": 5,
    "safety": 5,
    "condition": 5,
    "lightNoise": 5,
    "targetDistanceKm": 0,
    "lat": 0,
    "lng": 0,
    "notes": ""
  },
  {
    "id": "895375616",
    "title": "QuintoAndar 895375616",
    "neighborhood": "Itaim Bibi",
    "url": "https://www.quintoandar.com.br/imovel/895375616/alugar/apartamento-2-quartos-itaim-bibi-sao-paulo",
    "rent": 4500,
    "condo": 1300,
    "iptu": 25,
    "area": 75,
    "bedrooms": 2,
    "bathrooms": 1,
    "parking": 1,
    "transit": 5,
    "safety": 5,
    "condition": 5,
    "lightNoise": 5,
    "targetDistanceKm": 1.79,
    "lat": -23.6046205,
    "lng": -46.6780851,
    "notes": ""
  },
  {
    "id": "895300101",
    "title": "QuintoAndar ",
    "neighborhood": "",
    "url": "https://www.quintoandar.com.br/imovel/895300101/alugar/apartamento-2-quartos-itaim-bibi-sao-paulo",
    "rent": 0,
    "condo": 0,
    "iptu": 0,
    "area": 0,
    "bedrooms": 0,
    "bathrooms": 0,
    "parking": 0,
    "transit": 5,
    "safety": 5,
    "condition": 5,
    "lightNoise": 5,
    "targetDistanceKm": 0,
    "lat": 0,
    "lng": 0,
    "notes": ""
  },
  {
    "id": "895229486",
    "title": "QuintoAndar ",
    "neighborhood": "",
    "url": "https://www.quintoandar.com.br/imovel/895229486/alugar/apartamento-2-quartos-itaim-bibi-sao-paulo",
    "rent": 0,
    "condo": 0,
    "iptu": 0,
    "area": 0,
    "bedrooms": 0,
    "bathrooms": 0,
    "parking": 0,
    "transit": 5,
    "safety": 5,
    "condition": 5,
    "lightNoise": 5,
    "targetDistanceKm": 0,
    "lat": 0,
    "lng": 0,
    "notes": ""
  },
  {
    "id": "895055555",
    "title": "QuintoAndar ",
    "neighborhood": "",
    "url": "https://www.quintoandar.com.br/imovel/895055555/alugar/apartamento-2-quartos-itaim-bibi-sao-paulo",
    "rent": 0,
    "condo": 0,
    "iptu": 0,
    "area": 0,
    "bedrooms": 0,
    "bathrooms": 0,
    "parking": 0,
    "transit": 5,
    "safety": 5,
    "condition": 5,
    "lightNoise": 5,
    "targetDistanceKm": 0,
    "lat": 0,
    "lng": 0,
    "notes": ""
  }
]