{
  "scraped_at": "2026-06-20T12:41:19.348Z",
  "criteria": {
    "minBedrooms": 2,
    "maxRent": 9000,
    "maxTotalCost": 9000,
    "minArea": 50,
    "maxDistanceKm": 4.5,
    "allowedNeighborhoods": [
      "itaim bibi",
      "vila olímpia",
      "vila olimpia",
      "vila nova conceição",
      "vila nova conceicao",
      "jardim europa",
      "jardins"
    ],
    "preferredStreets": [
      "Rua Coronel Artur de Paula Ferreira",
      "Rua Santa Justina",
      "Rua Bueno Brandão",
      "Rua Balthazar da Veiga",
      "Rua Diogo Jácome",
      "Rua Afonso Braz",
      "Rua Lourenço Castanho",
      "Rua João Lourenço",
      "Rua Inhambu",
      "Rua Natividade",
      "Rua Monte Aprazível",
      "Rua Marcos Lopes",
      "Rua Quatá",
      "Rua Clodomiro Amazonas",
      "Rua Professor Filadelfo Azevedo",
      "Rua Bastos Pereira",
      "Avenida Santo Amaro",
      "Avenida República do Líbano",
      "Rua Groenlândia",
      "Rua Veneza",
      "Rua General Mena Barreto",
      "Rua Antonio Bento",
      "Rua Maestro Chiaffarelli",
      "Rua Maestro Elias Lobo",
      "Avenida Brasil",
      "Rua Gironda",
      "Rua Primavera",
      "Rua Ouro Branco",
      "Rua Oliveira Dias",
      "Alameda Joaquim Eugênio de Lima",
      "Rua Estados Unidos",
      "Rua Canadá",
      "Rua Cuba"
    ]
  },
  "total_candidates_checked": 94,
  "total_passed": 3,
  "total_failed": 0,
  "homes": [
    {
      "id": "893183447",
      "title": "QuintoAndar 893183447",
      "neighborhood": "Itaim Bibi",
      "street": "Rua Pais de Araújo",
      "url": "https://www.quintoandar.com.br/imovel/893183447/alugar/apartamento-2-quartos-itaim-bibi-sao-paulo",
      "rent": 5900,
      "condo": 1400,
      "iptu": 234,
      "area": 87,
      "bedrooms": 2,
      "bathrooms": 3,
      "parking": 1,
      "acceptsPets": true,
      "furnished": false,
      "features": {
        "balcony": false,
        "gourmetBalcony": false,
        "privatePool": false,
        "airConditioning": false,
        "gasShower": false,
        "box": true,
        "bedroomCabinets": true,
        "bathroomCabinets": true,
        "kitchenCabinets": true,
        "pool": false,
        "gym": true,
        "partyRoom": true,
        "gameRoom": false,
        "grill": false,
        "playground": true,
        "sauna": false,
        "doorman24h": true,
        "accessibleParking": true
      },
      "transit": 5,
      "safety": 5,
      "condition": 5,
      "lightNoise": 5,
      "targetDistanceKm": 0.58,
      "lat": -23.5837983,
      "lng": -46.6815296,
      "photos": [
        {
          "url": "https://www.quintoandar.com.br/img/med/893183447-73.47880335280588QA20231023S1828240I483447CorregioRuaPaisdeAraujo89apt93Eduardo87m23.jpg",
          "subtitle": "Sala",
          "cover": true
        },
        {
          "url": "https://www.quintoandar.com.br/img/med/893183447-6.803332352944946QA20231023S1828240I483447CorregioRuaPaisdeAraujo89apt93Eduardo87m211.jpg",
          "subtitle": "Sala",
          "cover": false
        },
        {
          "url": "https://www.quintoandar.com.br/img/med/893183447-452.2363239118QA20231023S1828240I483447CorregioRuaPaisdeAraujo89apt93Eduardo87m27.jpg",
          "subtitle": "Sala",
          "cover": false
        },
        {
          "url": "https://www.quintoandar.com.br/img/med/893183447-662.5684499219768QA20231023S1828240I483447CorregioRuaPaisdeAraujo89apt93Eduardo87m25.jpg",
          "subtitle": "Sala",
          "cover": false
        },
        {
          "url": "https://www.quintoandar.com.br/img/med/893183447-952.3924174054397QA20231023S1828240I483447CorregioRuaPaisdeAraujo89apt93Eduardo87m24.jpg",
          "subtitle": "Sala",
          "cover": false
        },
        {
          "url": "https://www.quintoandar.com.br/img/med/893183447-270.7246917295667QA20231023S1828240I483447CorregioRuaPaisdeAraujo89apt93Eduardo87m29.jpg",
          "subtitle": "Sala",
          "cover": false
        },
        {
          "url": "https://www.quintoandar.com.br/img/med/893183447-306.6506077867639QA20231023S1828240I483447CorregioRuaPaisdeAraujo89apt93Eduardo87m210.jpg",
          "subtitle": "Sala",
          "cover": false
        },
        {
          "url": "https://www.quintoandar.com.br/img/med/893183447-205.70150497719243QA20231023S1828240I483447CorregioRuaPaisdeAraujo89apt93Eduardo87m28.jpg",
          "subtitle": "Vista Sala",
          "cover": false
        },
        {
          "url": "https://www.quintoandar.com.br/img/med/893183447-178.9587132563536QA20231023S1828240I483447CorregioRuaPaisdeAraujo89apt93Eduardo87m214.jpg",
          "subtitle": "Corredor",
          "cover": false
        },
        {
          "url": "https://www.quintoandar.com.br/img/med/893183447-795.482911727708QA20231023S1828240I483447CorregioRuaPaisdeAraujo89apt93Eduardo87m215.jpg",
          "subtitle": "Quarto 1",
          "cover": false
        },
        {
          "url": "https://www.quintoandar.com.br/img/med/893183447-493.4633878437166QA20231023S1828240I483447CorregioRuaPaisdeAraujo89apt93Eduardo87m216.jpg",
          "subtitle": "Quarto 1",
          "cover": false
        },
        {
          "url": "https://www.quintoandar.com.br/img/med/893183447-208.26416169662875QA20231023S1828240I483447CorregioRuaPaisdeAraujo89apt93Eduardo87m217.jpg",
          "subtitle": "Quarto 1",
          "cover": false
        }
      ],
      "notes": "",
      "preferredStreet": false,
      "preferredStreetName": ""
    },
    {
      "id": "894870880",
      "title": "QuintoAndar 894870880",
      "neighborhood": "Itaim Bibi",
      "street": "Rua Hollywood",
      "url": "https://www.quintoandar.com.br/imovel/894870880/alugar/casa-3-quartos-itaim-bibi-sao-paulo",
      "rent": 7500,
      "condo": 0,
      "iptu": 668,
      "area": 250,
      "bedrooms": 3,
      "bathrooms": 3,
      "parking": 1,
      "acceptsPets": true,
      "furnished": true,
      "features": {
        "balcony": true,
        "gourmetBalcony": false,
        "privatePool": false,
        "airConditioning": false,
        "gasShower": false,
        "box": true,
        "bedroomCabinets": true,
        "bathroomCabinets": true,
        "kitchenCabinets": true,
        "pool": false,
        "gym": false,
        "partyRoom": false,
        "gameRoom": false,
        "grill": false,
        "playground": false,
        "sauna": false,
        "doorman24h": false,
        "accessibleParking": true
      },
      "transit": 5,
      "safety": 5,
      "condition": 5,
      "lightNoise": 5,
      "targetDistanceKm": 2.49,
      "lat": -23.6111459,
      "lng": -46.6858313,
      "photos": [
        {
          "url": "https://www.quintoandar.com.br/img/med/original894870880-187.17767831657417IMG99793.jpg",
          "subtitle": "Sala",
          "cover": true
        },
        {
          "url": "https://www.quintoandar.com.br/img/med/original894870880-45.11237517111999IMG99813.jpg",
          "subtitle": "Sala",
          "cover": false
        },
        {
          "url": "https://www.quintoandar.com.br/img/med/original894870880-864.2343320054395IMG99843.jpg",
          "subtitle": "Sala",
          "cover": false
        },
        {
          "url": "https://www.quintoandar.com.br/img/med/original894870880-623.7006540836095IMG99883.jpg",
          "subtitle": "Sala",
          "cover": false
        },
        {
          "url": "https://www.quintoandar.com.br/img/med/original894870880-219.93771009430873IMG99693.jpg",
          "subtitle": "Sala",
          "cover": false
        },
        {
          "url": "https://www.quintoandar.com.br/img/med/original894870880-253.4657224388186IMG99723.jpg",
          "subtitle": "Sala",
          "cover": false
        },
        {
          "url": "https://www.quintoandar.com.br/img/med/original894870880-224.46504979497485IMG99742.jpg",
          "subtitle": "Sala",
          "cover": false
        },
        {
          "url": "https://www.quintoandar.com.br/img/med/original894870880-474.27574170569164IMG99753.jpg",
          "subtitle": "Sala",
          "cover": false
        },
        {
          "url": "https://www.quintoandar.com.br/img/med/original894870880-318.9329001145172IMG99773.jpg",
          "subtitle": "Sala",
          "cover": false
        },
        {
          "url": "https://www.quintoandar.com.br/img/med/original894870880-994.075080062254IMG0005.jpg",
          "subtitle": "Quarto 1",
          "cover": false
        },
        {
          "url": "https://www.quintoandar.com.br/img/med/original894870880-694.6337519476937IMG0007.jpg",
          "subtitle": "Quarto 1",
          "cover": false
        },
        {
          "url": "https://www.quintoandar.com.br/img/med/original894870880-315.3076841304229IMG0010.jpg",
          "subtitle": "Quarto 1",
          "cover": false
        }
      ],
      "notes": "Aluguel: Casa mobiliada no Itaim Bibi com 3 quartos e varanda.",
      "preferredStreet": false,
      "preferredStreetName": ""
    },
    {
      "id": "894069890",
      "title": "QuintoAndar 894069890",
      "neighborhood": "Vila Olímpia",
      "street": "Avenida Doutor Cardoso de Melo",
      "url": "https://www.quintoandar.com.br/imovel/894069890/alugar/apartamento-2-quartos-vila-olimpia-sao-paulo",
      "rent": 4500,
      "condo": 1124,
      "iptu": 708,
      "area": 89,
      "bedrooms": 2,
      "bathrooms": 2,
      "parking": 1,
      "acceptsPets": true,
      "furnished": false,
      "features": {
        "balcony": false,
        "gourmetBalcony": false,
        "privatePool": false,
        "airConditioning": false,
        "gasShower": false,
        "box": true,
        "bedroomCabinets": true,
        "bathroomCabinets": true,
        "kitchenCabinets": true,
        "pool": false,
        "gym": false,
        "partyRoom": true,
        "gameRoom": false,
        "grill": false,
        "playground": false,
        "sauna": false,
        "doorman24h": true,
        "accessibleParking": false
      },
      "transit": 5,
      "safety": 5,
      "condition": 5,
      "lightNoise": 5,
      "targetDistanceKm": 1.43,
      "lat": -23.6014725,
      "lng": -46.6785313,
      "photos": [
        {
          "url": "https://www.quintoandar.com.br/img/med/894069890-793.71270083184191Sala1.jpg",
          "subtitle": "Sala",
          "cover": true
        },
        {
          "url": "https://www.quintoandar.com.br/img/med/894069890-764.0744163697781Sala2.jpg",
          "subtitle": "Sala",
          "cover": false
        },
        {
          "url": "https://www.quintoandar.com.br/img/med/894069890-431.8350118604991Sala3.jpg",
          "subtitle": "Sala",
          "cover": false
        },
        {
          "url": "https://www.quintoandar.com.br/img/med/894069890-110.044683964751091Sala4.jpg",
          "subtitle": "Sala",
          "cover": false
        },
        {
          "url": "https://www.quintoandar.com.br/img/med/894069890-14.085889655315321Sala5.jpg",
          "subtitle": "Sala",
          "cover": false
        },
        {
          "url": "https://www.quintoandar.com.br/img/med/894069890-129.32312756735421Sala6.jpg",
          "subtitle": "Sala",
          "cover": false
        },
        {
          "url": "https://www.quintoandar.com.br/img/med/894069890-104.717739847674962Q11.jpg",
          "subtitle": "Quarto 1",
          "cover": false
        },
        {
          "url": "https://www.quintoandar.com.br/img/med/894069890-540.3877587851892Q12.jpg",
          "subtitle": "Quarto 1",
          "cover": false
        },
        {
          "url": "https://www.quintoandar.com.br/img/med/894069890-442.622134001152Q13.jpg",
          "subtitle": "Quarto 1",
          "cover": false
        },
        {
          "url": "https://www.quintoandar.com.br/img/med/894069890-824.79268672958622Q14.jpg",
          "subtitle": "Quarto 1",
          "cover": false
        },
        {
          "url": "https://www.quintoandar.com.br/img/med/894069890-586.83173152691172Q15.jpg",
          "subtitle": "Quarto 1",
          "cover": false
        },
        {
          "url": "https://www.quintoandar.com.br/img/med/894069890-167.8653653870452S11.jpg",
          "subtitle": "Suíte",
          "cover": false
        }
      ],
      "notes": "Apartamento para alugar na Vila Olímpia, 2 quartos e aceita animais de estimação.",
      "preferredStreet": false,
      "preferredStreetName": ""
    }
  ],
  "failed_ids": []
}